sesiweb/__init__.py
sesiweb/exceptions.py
sesiweb/webapi.py
sesiweb/model/__init__.py
sesiweb/model/file.py
sesiweb/model/service.py
sesiweb-0.1.1.dist-info/LICENSE
sesiweb-0.1.1.dist-info/METADATA
sesiweb-0.1.1.dist-info/WHEEL
sesiweb-0.1.1.dist-info/top_level.txt
sesiweb-0.1.1.dist-info/RECORD
