Metadata-Version: 2.1
Name: sesiweb
Version: 0.1.1
Summary: Unofficial driver for the SideFX Web API
Author-email: Aaron Smith <aaron@aaronsmith.tv>
License: MIT License
Project-URL: Homepage, https://github.com/aaronsmithtv/sesiweb
Project-URL: Bug Reports, https://github.com/aaronsmithtv/issues
Project-URL: Source, https://github.com/aaronsmithtv/sesiweb/
Keywords: sidefx,houdini,sesi
Classifier: Development Status :: 3 - Alpha
Classifier: Intended Audience :: Developers
Classifier: License :: OSI Approved :: MIT License
Classifier: Topic :: Software Development :: Libraries
Classifier: Programming Language :: Python :: 3
Classifier: Operating System :: OS Independent
Requires-Python: >=3.7
License-File: LICENSE
Requires-Dist: requests
Requires-Dist: urllib3 (==1.26.5)
Requires-Dist: pydantic
Provides-Extra: dev
Requires-Dist: check-manifest ; extra == 'dev'
Provides-Extra: test
Requires-Dist: pytest ; extra == 'test'
Requires-Dist: coverage ; extra == 'test'
